AUTHORS
LICENSE
MANIFEST.in
README.rst
setup.py
django_userprofiles.egg-info/PKG-INFO
django_userprofiles.egg-info/SOURCES.txt
django_userprofiles.egg-info/dependency_links.txt
django_userprofiles.egg-info/not-zip-safe
django_userprofiles.egg-info/top_level.txt
userprofiles/__init__.py
userprofiles/admin.py
userprofiles/auth_backends.py
userprofiles/forms.py
userprofiles/mixins.py
userprofiles/models.py
userprofiles/settings.py
userprofiles/urls.py
userprofiles/utils.py
userprofiles/views.py
userprofiles/contrib/__init__.py
userprofiles/contrib/accountverification/__init__.py
userprofiles/contrib/accountverification/admin.py
userprofiles/contrib/accountverification/models.py
userprofiles/contrib/accountverification/urls.py
userprofiles/contrib/accountverification/views.py
userprofiles/contrib/accountverification/tests/__init__.py
userprofiles/contrib/accountverification/tests/test_models.py
userprofiles/contrib/accountverification/tests/test_views.py
userprofiles/contrib/emailverification/__init__.py
userprofiles/contrib/emailverification/admin.py
userprofiles/contrib/emailverification/forms.py
userprofiles/contrib/emailverification/models.py
userprofiles/contrib/emailverification/urls.py
userprofiles/contrib/emailverification/views.py
userprofiles/contrib/emailverification/tests/__init__.py
userprofiles/contrib/emailverification/tests/test_views.py
userprofiles/contrib/profiles/__init__.py
userprofiles/contrib/profiles/forms.py
userprofiles/contrib/profiles/models.py
userprofiles/contrib/profiles/urls.py
userprofiles/contrib/profiles/views.py
userprofiles/contrib/profiles/tests/__init__.py
userprofiles/contrib/profiles/tests/test_views.py
userprofiles/locale/de/LC_MESSAGES/django.mo
userprofiles/locale/de/LC_MESSAGES/django.po
userprofiles/templates/userprofiles/email_change.html
userprofiles/templates/userprofiles/email_change_requested.html
userprofiles/templates/userprofiles/logged_out.html
userprofiles/templates/userprofiles/login.html
userprofiles/templates/userprofiles/password_change.html
userprofiles/templates/userprofiles/password_change_done.html
userprofiles/templates/userprofiles/password_reset.html
