Metadata-Version: 1.1
Name: django-userprofiles
Version: 0.4
Summary: Registration, e-mail verifications and profiles.
Home-page: https://github.com/stephrdev/django-userprofiles/
Author: Stephan Jaekel
Author-email: steph@rdev.info
License: UNKNOWN
Platform: UNKNOWN
Classifier: Development Status :: 4 - Beta
Classifier: Environment :: Web Environment
Classifier: Intended Audience :: Developers
Classifier: License :: OSI Approved :: BSD License
Classifier: Operating System :: OS Independent
Classifier: Programming Language :: Python
Classifier: Framework :: Django
